.gitignore
7cbc11ae203aa630a28d__mypyc.cpython-311-darwin.so
asgi_headers-0.1.1.dist-info/METADATA
asgi_headers-0.1.1.dist-info/WHEEL
asgi_headers-0.1.1.dist-info/licenses/LICENSE
asgi_headers/__init__.cpython-311-darwin.so
asgi_headers/__init__.py
asgi_headers/core.cpython-311-darwin.so
asgi_headers/core.py
asgi_headers/types.cpython-311-darwin.so
asgi_headers/types.py
asgi_headers-0.1.1.dist-info/RECORD
